{
    "date_generated": "2025-12-05",
    "tickers": [
        "DNO.OL",
        "CADLR.OL",
        "SOMA.OL",
        "AUTO.OL",
        "BWE.OL",
        "VAR.OL"
    ],
    "data_last_date": "2025-12-04",
    "latest_prices": {
        "AUTO.OL": 11.199999809265137,
        "BWE.OL": 37.900001525878906,
        "CADLR.OL": 45.7599983215332,
        "DNO.OL": NaN,
        "SOMA.OL": 18.360000610351562,
        "VAR.OL": 31.75
    },
    "signal_date": "2025-12-30",
    "is_signal_day": false,
    "nav": NaN,
    "status": "signal-open",
    "entry_date": "2025-11-28",
    "exit_date": "2025-12-09",
    "entry_prices": {
        "DNO.OL": 14.510000228881836,
        "CADLR.OL": 44.58000183105469,
        "SOMA.OL": 18.200000762939453,
        "AUTO.OL": 11.0600004196167,
        "BWE.OL": 37.0,
        "VAR.OL": 31.6299991607666
    }
}