{
    "date_generated": "2026-07-17",
    "tickers": [
        "DNO.OL",
        "CADLR.OL",
        "SOMA.OL",
        "AUTO.OL",
        "BWE.OL",
        "VAR.OL"
    ],
    "data_last_date": "2026-07-17",
    "latest_prices": {
        "AUTO.OL": 11.069999694824219,
        "BWE.OL": 51.099998474121094,
        "CADLR.OL": 56.20000076293945,
        "DNO.OL": 17.030000686645508,
        "SOMA.OL": 26.549999237060547,
        "VAR.OL": 44.470001220703125
    },
    "signal_date": "2026-07-31",
    "is_signal_day": false,
    "nav": NaN,
    "status": "no-signal",
    "message": "No positions entered today."
}