{
    "date_generated": "2025-12-08",
    "tickers": [
        "DNO.OL",
        "CADLR.OL",
        "SOMA.OL",
        "AUTO.OL",
        "BWE.OL",
        "VAR.OL"
    ],
    "data_last_date": "2025-12-08",
    "latest_prices": {
        "AUTO.OL": 11.510000228881836,
        "BWE.OL": 39.29999923706055,
        "CADLR.OL": 47.279998779296875,
        "DNO.OL": 15.239999771118164,
        "SOMA.OL": 18.540000915527344,
        "VAR.OL": 32.29999923706055
    },
    "signal_date": "2025-12-30",
    "is_signal_day": false,
    "nav": 51931.88209042895,
    "status": "signal-open",
    "entry_date": "2025-11-28",
    "exit_date": "2025-12-09",
    "entry_prices": {
        "DNO.OL": 14.510000228881836,
        "CADLR.OL": 44.58000183105469,
        "SOMA.OL": 18.200000762939453,
        "AUTO.OL": 11.0600004196167,
        "BWE.OL": 37.0,
        "VAR.OL": 31.6299991607666
    }
}