[
  {
    "Ticker":"GJF.OL",
    "3D_Return":-0.0308219178,
    "Signal":"HOLD",
    "LastPrice":283.0,
    "Date":"2026-01-13 13:27 UTC"
  },
  {
    "Ticker":"KID.OL",
    "3D_Return":-0.0212443322,
    "Signal":"HOLD",
    "LastPrice":129.0,
    "Date":"2026-01-13 13:27 UTC"
  },
  {
    "Ticker":"SBNOR.OL",
    "3D_Return":-0.0140844913,
    "Signal":"HOLD",
    "LastPrice":189.0,
    "Date":"2026-01-13 13:27 UTC"
  },
  {
    "Ticker":"AFG.OL",
    "3D_Return":-0.012861785,
    "Signal":"HOLD",
    "LastPrice":184.199997,
    "Date":"2026-01-13 13:27 UTC"
  },
  {
    "Ticker":"STB.OL",
    "3D_Return":-0.0110208467,
    "Signal":"HOLD",
    "LastPrice":170.5,
    "Date":"2026-01-13 13:27 UTC"
  },
  {
    "Ticker":"NONG.OL",
    "3D_Return":-0.0100066715,
    "Signal":"HOLD",
    "LastPrice":148.399994,
    "Date":"2026-01-13 13:27 UTC"
  },
  {
    "Ticker":"MORG.OL",
    "3D_Return":-0.0093913203,
    "Signal":"HOLD",
    "LastPrice":113.919998,
    "Date":"2026-01-13 13:27 UTC"
  },
  {
    "Ticker":"VEI.OL",
    "3D_Return":-0.0055555556,
    "Signal":"HOLD",
    "LastPrice":179.0,
    "Date":"2026-01-13 13:27 UTC"
  },
  {
    "Ticker":"EPR.OL",
    "3D_Return":-0.0053705694,
    "Signal":"HOLD",
    "LastPrice":92.599998,
    "Date":"2026-01-13 13:27 UTC"
  },
  {
    "Ticker":"MING.OL",
    "3D_Return":-0.0053405763,
    "Signal":"HOLD",
    "LastPrice":197.419998,
    "Date":"2026-01-13 13:27 UTC"
  },
  {
    "Ticker":"SB1NO.OL",
    "3D_Return":0.0036119553,
    "Signal":"HOLD",
    "LastPrice":194.5,
    "Date":"2026-01-13 13:27 UTC"
  },
  {
    "Ticker":"ORK.OL",
    "3D_Return":0.0045045045,
    "Signal":"HOLD",
    "LastPrice":111.5,
    "Date":"2026-01-13 13:27 UTC"
  },
  {
    "Ticker":"DNB.OL",
    "3D_Return":0.0054151625,
    "Signal":"HOLD",
    "LastPrice":278.5,
    "Date":"2026-01-13 13:27 UTC"
  },
  {
    "Ticker":"PROT.OL",
    "3D_Return":0.0191204589,
    "Signal":"HOLD",
    "LastPrice":533.0,
    "Date":"2026-01-13 13:27 UTC"
  }
]