[
  {
    "Ticker":"KID.OL",
    "3D_Return":-0.0217028885,
    "Signal":"HOLD",
    "LastPrice":117.199997,
    "Date":"2026-07-01 11:54 UTC"
  },
  {
    "Ticker":"MING.OL",
    "3D_Return":-0.0210978753,
    "Signal":"HOLD",
    "LastPrice":186.520004,
    "Date":"2026-07-01 11:54 UTC"
  },
  {
    "Ticker":"EPR.OL",
    "3D_Return":-0.0146067759,
    "Signal":"HOLD",
    "LastPrice":87.699997,
    "Date":"2026-07-01 11:54 UTC"
  },
  {
    "Ticker":"VEI.OL",
    "3D_Return":-0.0135982787,
    "Signal":"HOLD",
    "LastPrice":188.600006,
    "Date":"2026-07-01 11:54 UTC"
  },
  {
    "Ticker":"MORG.OL",
    "3D_Return":-0.0135184811,
    "Signal":"HOLD",
    "LastPrice":108.0,
    "Date":"2026-07-01 11:54 UTC"
  },
  {
    "Ticker":"NONG.OL",
    "3D_Return":-0.0107400093,
    "Signal":"HOLD",
    "LastPrice":151.059998,
    "Date":"2026-07-01 11:54 UTC"
  },
  {
    "Ticker":"SB1NO.OL",
    "3D_Return":-0.0082901871,
    "Signal":"HOLD",
    "LastPrice":191.399994,
    "Date":"2026-07-01 11:54 UTC"
  },
  {
    "Ticker":"AFG.OL",
    "3D_Return":-0.0071794559,
    "Signal":"HOLD",
    "LastPrice":193.600006,
    "Date":"2026-07-01 11:54 UTC"
  },
  {
    "Ticker":"SBNOR.OL",
    "3D_Return":-0.0023887212,
    "Signal":"HOLD",
    "LastPrice":183.759995,
    "Date":"2026-07-01 11:54 UTC"
  },
  {
    "Ticker":"DNB.OL",
    "3D_Return":-0.0010228019,
    "Signal":"HOLD",
    "LastPrice":293.0,
    "Date":"2026-07-01 11:54 UTC"
  },
  {
    "Ticker":"ORK.OL",
    "3D_Return":-0.0009497256,
    "Signal":"HOLD",
    "LastPrice":105.199997,
    "Date":"2026-07-01 11:54 UTC"
  },
  {
    "Ticker":"PROT.OL",
    "3D_Return":0.0041876046,
    "Signal":"HOLD",
    "LastPrice":479.600006,
    "Date":"2026-07-01 11:54 UTC"
  },
  {
    "Ticker":"GJF.OL",
    "3D_Return":0.0060015231,
    "Signal":"HOLD",
    "LastPrice":268.200012,
    "Date":"2026-07-01 11:54 UTC"
  },
  {
    "Ticker":"STB.OL",
    "3D_Return":0.0126165826,
    "Signal":"HOLD",
    "LastPrice":184.600006,
    "Date":"2026-07-01 11:54 UTC"
  }
]