[
  {
    "Ticker":"PROT.OL",
    "3D_Return":-0.0339622642,
    "Signal":"HOLD",
    "LastPrice":512.0,
    "Date":"2026-03-20 13:46 UTC"
  },
  {
    "Ticker":"ORK.OL",
    "3D_Return":-0.0269814249,
    "Signal":"HOLD",
    "LastPrice":115.400002,
    "Date":"2026-03-20 13:46 UTC"
  },
  {
    "Ticker":"STB.OL",
    "3D_Return":-0.025684932,
    "Signal":"HOLD",
    "LastPrice":170.699997,
    "Date":"2026-03-20 13:46 UTC"
  },
  {
    "Ticker":"GJF.OL",
    "3D_Return":-0.0223214296,
    "Signal":"HOLD",
    "LastPrice":262.799988,
    "Date":"2026-03-20 13:46 UTC"
  },
  {
    "Ticker":"KID.OL",
    "3D_Return":-0.0196078554,
    "Signal":"HOLD",
    "LastPrice":120.0,
    "Date":"2026-03-20 13:46 UTC"
  },
  {
    "Ticker":"EPR.OL",
    "3D_Return":-0.016538038,
    "Signal":"HOLD",
    "LastPrice":89.199997,
    "Date":"2026-03-20 13:46 UTC"
  },
  {
    "Ticker":"AFG.OL",
    "3D_Return":-0.0158192263,
    "Signal":"HOLD",
    "LastPrice":174.199997,
    "Date":"2026-03-20 13:46 UTC"
  },
  {
    "Ticker":"SBNOR.OL",
    "3D_Return":-0.0139651025,
    "Signal":"HOLD",
    "LastPrice":197.699997,
    "Date":"2026-03-20 13:46 UTC"
  },
  {
    "Ticker":"MORG.OL",
    "3D_Return":-0.0119801602,
    "Signal":"HOLD",
    "LastPrice":115.459999,
    "Date":"2026-03-20 13:46 UTC"
  },
  {
    "Ticker":"VEI.OL",
    "3D_Return":-0.0072388518,
    "Signal":"HOLD",
    "LastPrice":192.0,
    "Date":"2026-03-20 13:46 UTC"
  },
  {
    "Ticker":"MING.OL",
    "3D_Return":0.0048134777,
    "Signal":"HOLD",
    "LastPrice":208.75,
    "Date":"2026-03-20 13:46 UTC"
  },
  {
    "Ticker":"NONG.OL",
    "3D_Return":0.005714247,
    "Signal":"HOLD",
    "LastPrice":158.399994,
    "Date":"2026-03-20 13:46 UTC"
  },
  {
    "Ticker":"DNB.OL",
    "3D_Return":0.0085470085,
    "Signal":"HOLD",
    "LastPrice":295.0,
    "Date":"2026-03-20 13:46 UTC"
  },
  {
    "Ticker":"SB1NO.OL",
    "3D_Return":0.0174129353,
    "Signal":"HOLD",
    "LastPrice":204.5,
    "Date":"2026-03-20 13:46 UTC"
  }
]