[
  {
    "Ticker":"MORG.OL",
    "3D_Return":-0.0242271844,
    "Signal":"HOLD",
    "LastPrice":116.800003,
    "Date":"2026-03-18 13:52 UTC"
  },
  {
    "Ticker":"PROT.OL",
    "3D_Return":-0.0114285714,
    "Signal":"HOLD",
    "LastPrice":519.0,
    "Date":"2026-03-18 13:52 UTC"
  },
  {
    "Ticker":"SB1NO.OL",
    "3D_Return":-0.0048543689,
    "Signal":"HOLD",
    "LastPrice":205.0,
    "Date":"2026-03-18 13:52 UTC"
  },
  {
    "Ticker":"ORK.OL",
    "3D_Return":-0.0033726942,
    "Signal":"HOLD",
    "LastPrice":118.199997,
    "Date":"2026-03-18 13:52 UTC"
  },
  {
    "Ticker":"EPR.OL",
    "3D_Return":0.0,
    "Signal":"HOLD",
    "LastPrice":90.699997,
    "Date":"2026-03-18 13:52 UTC"
  },
  {
    "Ticker":"NONG.OL",
    "3D_Return":0.0031486145,
    "Signal":"HOLD",
    "LastPrice":159.300003,
    "Date":"2026-03-18 13:52 UTC"
  },
  {
    "Ticker":"GJF.OL",
    "3D_Return":0.0044842364,
    "Signal":"HOLD",
    "LastPrice":268.799988,
    "Date":"2026-03-18 13:52 UTC"
  },
  {
    "Ticker":"KID.OL",
    "3D_Return":0.004934198,
    "Signal":"HOLD",
    "LastPrice":122.199997,
    "Date":"2026-03-18 13:52 UTC"
  },
  {
    "Ticker":"MING.OL",
    "3D_Return":0.0073651845,
    "Signal":"HOLD",
    "LastPrice":212.0,
    "Date":"2026-03-18 13:52 UTC"
  },
  {
    "Ticker":"VEI.OL",
    "3D_Return":0.0092879413,
    "Signal":"HOLD",
    "LastPrice":195.600006,
    "Date":"2026-03-18 13:52 UTC"
  },
  {
    "Ticker":"SBNOR.OL",
    "3D_Return":0.0114798489,
    "Signal":"HOLD",
    "LastPrice":202.649994,
    "Date":"2026-03-18 13:52 UTC"
  },
  {
    "Ticker":"DNB.OL",
    "3D_Return":0.0140942117,
    "Signal":"HOLD",
    "LastPrice":295.0,
    "Date":"2026-03-18 13:52 UTC"
  },
  {
    "Ticker":"AFG.OL",
    "3D_Return":0.0169491525,
    "Signal":"HOLD",
    "LastPrice":180.0,
    "Date":"2026-03-18 13:52 UTC"
  },
  {
    "Ticker":"STB.OL",
    "3D_Return":0.0231749702,
    "Signal":"HOLD",
    "LastPrice":176.600006,
    "Date":"2026-03-18 13:52 UTC"
  }
]