[
  {
    "Ticker":"MING.OL",
    "3D_Return":-0.0153248571,
    "Signal":"HOLD",
    "LastPrice":187.619995,
    "Date":"2026-07-01 08:51 UTC"
  },
  {
    "Ticker":"EPR.OL",
    "3D_Return":-0.0146067759,
    "Signal":"HOLD",
    "LastPrice":87.699997,
    "Date":"2026-07-01 08:51 UTC"
  },
  {
    "Ticker":"AFG.OL",
    "3D_Return":-0.0133333646,
    "Signal":"HOLD",
    "LastPrice":192.399994,
    "Date":"2026-07-01 08:51 UTC"
  },
  {
    "Ticker":"KID.OL",
    "3D_Return":-0.011686156,
    "Signal":"HOLD",
    "LastPrice":118.400002,
    "Date":"2026-07-01 08:51 UTC"
  },
  {
    "Ticker":"VEI.OL",
    "3D_Return":-0.0104602512,
    "Signal":"HOLD",
    "LastPrice":189.199997,
    "Date":"2026-07-01 08:51 UTC"
  },
  {
    "Ticker":"NONG.OL",
    "3D_Return":-0.0044531283,
    "Signal":"HOLD",
    "LastPrice":152.020004,
    "Date":"2026-07-01 08:51 UTC"
  },
  {
    "Ticker":"SB1NO.OL",
    "3D_Return":-0.0010362536,
    "Signal":"HOLD",
    "LastPrice":192.800003,
    "Date":"2026-07-01 08:51 UTC"
  },
  {
    "Ticker":"ORK.OL",
    "3D_Return":-0.0009497256,
    "Signal":"HOLD",
    "LastPrice":105.199997,
    "Date":"2026-07-01 08:51 UTC"
  },
  {
    "Ticker":"DNB.OL",
    "3D_Return":0.0023866766,
    "Signal":"HOLD",
    "LastPrice":294.0,
    "Date":"2026-07-01 08:51 UTC"
  },
  {
    "Ticker":"PROT.OL",
    "3D_Return":0.0046063268,
    "Signal":"HOLD",
    "LastPrice":479.799988,
    "Date":"2026-07-01 08:51 UTC"
  },
  {
    "Ticker":"GJF.OL",
    "3D_Return":0.0090022275,
    "Signal":"HOLD",
    "LastPrice":269.0,
    "Date":"2026-07-01 08:51 UTC"
  },
  {
    "Ticker":"SBNOR.OL",
    "3D_Return":0.0108577635,
    "Signal":"HOLD",
    "LastPrice":186.199997,
    "Date":"2026-07-01 08:51 UTC"
  },
  {
    "Ticker":"STB.OL",
    "3D_Return":0.0170048864,
    "Signal":"HOLD",
    "LastPrice":185.399994,
    "Date":"2026-07-01 08:51 UTC"
  },
  {
    "Ticker":"MORG.OL",
    "3D_Return":null,
    "Signal":"HOLD",
    "LastPrice":108.339996,
    "Date":"2026-06-30 08:51 UTC"
  }
]