[
  {
    "Ticker":"EPR.OL",
    "3D_Return":-0.05911825,
    "Signal":"HOLD",
    "LastPrice":93.900002,
    "Date":"2026-05-04 13:04 UTC"
  },
  {
    "Ticker":"SBNOR.OL",
    "3D_Return":-0.0411764407,
    "Signal":"HOLD",
    "LastPrice":195.600006,
    "Date":"2026-05-04 13:04 UTC"
  },
  {
    "Ticker":"PROT.OL",
    "3D_Return":-0.0217576407,
    "Signal":"HOLD",
    "LastPrice":458.600006,
    "Date":"2026-05-04 13:04 UTC"
  },
  {
    "Ticker":"MING.OL",
    "3D_Return":-0.0161407182,
    "Signal":"HOLD",
    "LastPrice":204.199997,
    "Date":"2026-05-04 13:04 UTC"
  },
  {
    "Ticker":"SB1NO.OL",
    "3D_Return":-0.0140000153,
    "Signal":"HOLD",
    "LastPrice":197.199997,
    "Date":"2026-05-04 13:04 UTC"
  },
  {
    "Ticker":"KID.OL",
    "3D_Return":-0.013574683,
    "Signal":"HOLD",
    "LastPrice":130.800003,
    "Date":"2026-05-04 13:04 UTC"
  },
  {
    "Ticker":"MORG.OL",
    "3D_Return":-0.0059471112,
    "Signal":"HOLD",
    "LastPrice":113.660004,
    "Date":"2026-05-04 13:04 UTC"
  },
  {
    "Ticker":"ORK.OL",
    "3D_Return":0.0026571782,
    "Signal":"HOLD",
    "LastPrice":113.199997,
    "Date":"2026-05-04 13:04 UTC"
  },
  {
    "Ticker":"DNB.OL",
    "3D_Return":0.0046762151,
    "Signal":"HOLD",
    "LastPrice":279.299988,
    "Date":"2026-05-04 13:04 UTC"
  },
  {
    "Ticker":"GJF.OL",
    "3D_Return":0.0054945414,
    "Signal":"HOLD",
    "LastPrice":256.200012,
    "Date":"2026-05-04 13:04 UTC"
  },
  {
    "Ticker":"VEI.OL",
    "3D_Return":0.0086486816,
    "Signal":"HOLD",
    "LastPrice":186.600006,
    "Date":"2026-05-04 13:04 UTC"
  },
  {
    "Ticker":"AFG.OL",
    "3D_Return":0.0125714111,
    "Signal":"HOLD",
    "LastPrice":177.199997,
    "Date":"2026-05-04 13:04 UTC"
  },
  {
    "Ticker":"STB.OL",
    "3D_Return":0.0590691738,
    "Signal":"HOLD",
    "LastPrice":177.5,
    "Date":"2026-05-04 13:04 UTC"
  }
]